awesto_djangocms_carousel-0.3.0.dist-info/DESCRIPTION.rst
awesto_djangocms_carousel-0.3.0.dist-info/METADATA
awesto_djangocms_carousel-0.3.0.dist-info/RECORD
awesto_djangocms_carousel-0.3.0.dist-info/WHEEL
awesto_djangocms_carousel-0.3.0.dist-info/metadata.json
awesto_djangocms_carousel-0.3.0.dist-info/top_level.txt
cmsplugin_carousel/__init__.py
cmsplugin_carousel/cms_plugins.py
cmsplugin_carousel/models.py
cmsplugin_carousel/settings_test.py
cmsplugin_carousel/migrations/0001_initial.py
cmsplugin_carousel/migrations/0002_auto_20170223_2039.py
cmsplugin_carousel/migrations/__init__.py
cmsplugin_carousel/templates/cmsplugin_carousel/caption.html
cmsplugin_carousel/templates/cmsplugin_carousel/carousel.html
