Metadata-Version: 2.0
Name: awesto-djangocms-carousel
Version: 0.3.0
Summary: A carousel plugin for djangoCMS
Home-page: https://github.com/awesto/djangocms-carousel
Author: René Fleschenberg
Author-email: rene@fleschenberg.net
License: MIT
Platform: UNKNOWN
Classifier: Development Status :: 5 - Production/Stable
Classifier: Intended Audience :: Developers
Classifier: License :: OSI Approved :: MIT License
Classifier: Operating System :: Unix
Classifier: Operating System :: POSIX
Classifier: Operating System :: Microsoft :: Windows
Classifier: Programming Language :: Python
Classifier: Programming Language :: Python :: 3.4
Classifier: Programming Language :: Python :: 3.5
Classifier: Programming Language :: Python :: Implementation :: CPython
Classifier: Programming Language :: Python :: Implementation :: PyPy
Classifier: Topic :: Utilities
Requires-Dist: Django (<1.10,>=1.8.5)
Requires-Dist: django-admin-sortable (<=2.0.18)
Requires-Dist: django-cms (>=3.3.3)
Requires-Dist: django-filer (>=1.2.6)
